Metadata-Version: 1.1
Name: task-runner
Version: 0.0.1
Summary: TaskRunner
Home-page: https://github.com/kfichter/task-runner
Author: Kelvin Fichter
Author-email: UNKNOWN
License: MIT
Keywords: sneaker bot development
Platform: UNKNOWN
Classifier: Development Status :: 3 - Alpha
Classifier: Intended Audience :: Developers
Classifier: Topic :: Software Development :: Libraries :: Python Modules
Classifier: License :: OSI Approved :: MIT License
Classifier: Programming Language :: Python :: 2
Classifier: Programming Language :: Python :: 2.7
Classifier: Programming Language :: Python :: 3
Classifier: Programming Language :: Python :: 3.3
Classifier: Programming Language :: Python :: 3.4
Classifier: Programming Language :: Python :: 3.5
